eventsflow/cli.py
eventsflow/events.py
eventsflow/utils.py
eventsflow/flow/__init__.py
eventsflow/flow/parser.py
eventsflow/flow/settings.py
eventsflow/queues/local/__init__.py
eventsflow/queues/local/context.py
eventsflow/queues/local/queues.py
eventsflow/registries/queues.py
eventsflow/registries/workers.py
eventsflow/workers/asyncio.py
eventsflow/workers/process.py
eventsflow/workers/settings.py
eventsflow-0.1.3.dist-info/LICENSE
eventsflow-0.1.3.dist-info/METADATA
eventsflow-0.1.3.dist-info/WHEEL
eventsflow-0.1.3.dist-info/entry_points.txt
eventsflow-0.1.3.dist-info/top_level.txt
eventsflow-0.1.3.dist-info/RECORD
