Metadata-Version: 2.1
Name: eventsflow
Version: 0.1.3
Summary: Events Flow
Home-page: UNKNOWN
License: UNKNOWN
Platform: UNKNOWN
Classifier: Programming Language :: Python :: 3
Classifier: Programming Language :: Python :: 3.5
Classifier: Programming Language :: Python :: 3.6
Classifier: Programming Language :: Python :: Implementation :: CPython
Classifier: License :: OSI Approved :: MIT License
Classifier: Operating System :: Unix
Requires-Python: >=3.5
Requires-Dist: jinja2 (==2.10.1)
Requires-Dist: pyyaml (==5.1)
